{"trial_id": "067", "hyperparameters": {"space": [{"class_name": "Int", "config": {"name": "Dense_layers", "default": null, "conditions": [], "min_value": 1, "max_value": 10, "step": 1, "sampling": "linear"}}, {"class_name": "Int", "config": {"name": "Dense_0", "default": 50, "conditions": [], "min_value": 5, "max_value": 512, "step": 1, "sampling": "linear"}}, {"class_name": "Choice", "config": {"name": "Activation_0", "default": "relu", "conditions": [], "values": ["relu", "tanh"], "ordered": false}}, {"class_name": "Float", "config": {"name": "KernelRegularizer_0", "default": 1e-10, "conditions": [], "min_value": 1e-10, "max_value": 0.5, "step": null, "sampling": "log"}}, {"class_name": "Float", "config": {"name": "ActivityRegularizer_0", "default": 1e-10, "conditions": [], "min_value": 1e-10, "max_value": 0.5, "step": null, "sampling": "log"}}, {"class_name": "Float", "config": {"name": "Dropout_0", "default": 1e-06, "conditions": [], "min_value": 1e-06, "max_value": 0.5, "step": null, "sampling": "log"}}, {"class_name": "Float", "config": {"name": "LearningRate", "default": 0.0001, "conditions": [], "min_value": 0.0001, "max_value": 0.01, "step": null, "sampling": "log"}}, {"class_name": "Int", "config": {"name": "Dense_1", "default": 50, "conditions": [], "min_value": 5, "max_value": 512, "step": 1, "sampling": "linear"}}, {"class_name": "Choice", "config": {"name": "Activation_1", "default": "relu", "conditions": [], "values": ["relu", "tanh"], "ordered": false}}, {"class_name": "Float", "config": {"name": "KernelRegularizer_1", "default": 1e-10, "conditions": [], "min_value": 1e-10, "max_value": 0.5, "step": null, "sampling": "log"}}, {"class_name": "Float", "config": {"name": "ActivityRegularizer_1", "default": 1e-10, "conditions": [], "min_value": 1e-10, "max_value": 0.5, "step": null, "sampling": "log"}}, {"class_name": "Float", "config": {"name": "Dropout_1", "default": 1e-06, "conditions": [], "min_value": 1e-06, "max_value": 0.5, "step": null, "sampling": "log"}}, {"class_name": "Int", "config": {"name": "Dense_2", "default": 50, "conditions": [], "min_value": 5, "max_value": 512, "step": 1, "sampling": "linear"}}, {"class_name": "Choice", "config": {"name": "Activation_2", "default": "relu", "conditions": [], "values": ["relu", "tanh"], "ordered": false}}, {"class_name": "Float", "config": {"name": "KernelRegularizer_2", "default": 1e-10, "conditions": [], "min_value": 1e-10, "max_value": 0.5, "step": null, "sampling": "log"}}, {"class_name": "Float", "config": {"name": "ActivityRegularizer_2", "default": 1e-10, "conditions": [], "min_value": 1e-10, "max_value": 0.5, "step": null, "sampling": "log"}}, {"class_name": "Float", "config": {"name": "Dropout_2", "default": 1e-06, "conditions": [], "min_value": 1e-06, "max_value": 0.5, "step": null, "sampling": "log"}}, {"class_name": "Int", "config": {"name": "Dense_3", "default": 50, "conditions": [], "min_value": 5, "max_value": 512, "step": 1, "sampling": "linear"}}, {"class_name": "Choice", "config": {"name": "Activation_3", "default": "relu", "conditions": [], "values": ["relu", "tanh"], "ordered": false}}, {"class_name": "Float", "config": {"name": "KernelRegularizer_3", "default": 1e-10, "conditions": [], "min_value": 1e-10, "max_value": 0.5, "step": null, "sampling": "log"}}, {"class_name": "Float", "config": {"name": "ActivityRegularizer_3", "default": 1e-10, "conditions": [], "min_value": 1e-10, "max_value": 0.5, "step": null, "sampling": "log"}}, {"class_name": "Float", "config": {"name": "Dropout_3", "default": 1e-06, "conditions": [], "min_value": 1e-06, "max_value": 0.5, "step": null, "sampling": "log"}}, {"class_name": "Int", "config": {"name": "Dense_4", "default": 50, "conditions": [], "min_value": 5, "max_value": 512, "step": 1, "sampling": "linear"}}, {"class_name": "Choice", "config": {"name": "Activation_4", "default": "relu", "conditions": [], "values": ["relu", "tanh"], "ordered": false}}, {"class_name": "Float", "config": {"name": "KernelRegularizer_4", "default": 1e-10, "conditions": [], "min_value": 1e-10, "max_value": 0.5, "step": null, "sampling": "log"}}, {"class_name": "Float", "config": {"name": "ActivityRegularizer_4", "default": 1e-10, "conditions": [], "min_value": 1e-10, "max_value": 0.5, "step": null, "sampling": "log"}}, {"class_name": "Float", "config": {"name": "Dropout_4", "default": 1e-06, "conditions": [], "min_value": 1e-06, "max_value": 0.5, "step": null, "sampling": "log"}}, {"class_name": "Int", "config": {"name": "Dense_5", "default": 50, "conditions": [], "min_value": 5, "max_value": 512, "step": 1, "sampling": "linear"}}, {"class_name": "Choice", "config": {"name": "Activation_5", "default": "relu", "conditions": [], "values": ["relu", "tanh"], "ordered": false}}, {"class_name": "Float", "config": {"name": "KernelRegularizer_5", "default": 1e-10, "conditions": [], "min_value": 1e-10, "max_value": 0.5, "step": null, "sampling": "log"}}, {"class_name": "Float", "config": {"name": "ActivityRegularizer_5", "default": 1e-10, "conditions": [], "min_value": 1e-10, "max_value": 0.5, "step": null, "sampling": "log"}}, {"class_name": "Float", "config": {"name": "Dropout_5", "default": 1e-06, "conditions": [], "min_value": 1e-06, "max_value": 0.5, "step": null, "sampling": "log"}}, {"class_name": "Int", "config": {"name": "Dense_6", "default": 50, "conditions": [], "min_value": 5, "max_value": 512, "step": 1, "sampling": "linear"}}, {"class_name": "Choice", "config": {"name": "Activation_6", "default": "relu", "conditions": [], "values": ["relu", "tanh"], "ordered": false}}, {"class_name": "Float", "config": {"name": "KernelRegularizer_6", "default": 1e-10, "conditions": [], "min_value": 1e-10, "max_value": 0.5, "step": null, "sampling": "log"}}, {"class_name": "Float", "config": {"name": "ActivityRegularizer_6", "default": 1e-10, "conditions": [], "min_value": 1e-10, "max_value": 0.5, "step": null, "sampling": "log"}}, {"class_name": "Float", "config": {"name": "Dropout_6", "default": 1e-06, "conditions": [], "min_value": 1e-06, "max_value": 0.5, "step": null, "sampling": "log"}}, {"class_name": "Int", "config": {"name": "Dense_7", "default": 50, "conditions": [], "min_value": 5, "max_value": 512, "step": 1, "sampling": "linear"}}, {"class_name": "Choice", "config": {"name": "Activation_7", "default": "relu", "conditions": [], "values": ["relu", "tanh"], "ordered": false}}, {"class_name": "Float", "config": {"name": "KernelRegularizer_7", "default": 1e-10, "conditions": [], "min_value": 1e-10, "max_value": 0.5, "step": null, "sampling": "log"}}, {"class_name": "Float", "config": {"name": "ActivityRegularizer_7", "default": 1e-10, "conditions": [], "min_value": 1e-10, "max_value": 0.5, "step": null, "sampling": "log"}}, {"class_name": "Float", "config": {"name": "Dropout_7", "default": 1e-06, "conditions": [], "min_value": 1e-06, "max_value": 0.5, "step": null, "sampling": "log"}}, {"class_name": "Int", "config": {"name": "Dense_8", "default": 50, "conditions": [], "min_value": 5, "max_value": 512, "step": 1, "sampling": "linear"}}, {"class_name": "Choice", "config": {"name": "Activation_8", "default": "relu", "conditions": [], "values": ["relu", "tanh"], "ordered": false}}, {"class_name": "Float", "config": {"name": "KernelRegularizer_8", "default": 1e-10, "conditions": [], "min_value": 1e-10, "max_value": 0.5, "step": null, "sampling": "log"}}, {"class_name": "Float", "config": {"name": "ActivityRegularizer_8", "default": 1e-10, "conditions": [], "min_value": 1e-10, "max_value": 0.5, "step": null, "sampling": "log"}}, {"class_name": "Float", "config": {"name": "Dropout_8", "default": 1e-06, "conditions": [], "min_value": 1e-06, "max_value": 0.5, "step": null, "sampling": "log"}}, {"class_name": "Int", "config": {"name": "Dense_9", "default": 50, "conditions": [], "min_value": 5, "max_value": 512, "step": 1, "sampling": "linear"}}, {"class_name": "Choice", "config": {"name": "Activation_9", "default": "relu", "conditions": [], "values": ["relu", "tanh"], "ordered": false}}, {"class_name": "Float", "config": {"name": "KernelRegularizer_9", "default": 1e-10, "conditions": [], "min_value": 1e-10, "max_value": 0.5, "step": null, "sampling": "log"}}, {"class_name": "Float", "config": {"name": "ActivityRegularizer_9", "default": 1e-10, "conditions": [], "min_value": 1e-10, "max_value": 0.5, "step": null, "sampling": "log"}}, {"class_name": "Float", "config": {"name": "Dropout_9", "default": 1e-06, "conditions": [], "min_value": 1e-06, "max_value": 0.5, "step": null, "sampling": "log"}}], "values": {"Dense_layers": 7, "Dense_0": 47, "Activation_0": "relu", "KernelRegularizer_0": 6.664060188698731e-07, "ActivityRegularizer_0": 0.00020130063977795944, "Dropout_0": 7.672567328747461e-06, "LearningRate": 0.004845482567128109, "Dense_1": 388, "Activation_1": "tanh", "KernelRegularizer_1": 4.368516200480487e-06, "ActivityRegularizer_1": 8.037306047615627e-06, "Dropout_1": 0.0008758507430503017, "Dense_2": 214, "Activation_2": "tanh", "KernelRegularizer_2": 4.972152485828148e-08, "ActivityRegularizer_2": 2.1012787866454523e-10, "Dropout_2": 0.010355415515787298, "Dense_3": 234, "Activation_3": "tanh", "KernelRegularizer_3": 1.7202235878519439e-07, "ActivityRegularizer_3": 0.3924234420302133, "Dropout_3": 0.012092724208852402, "Dense_4": 433, "Activation_4": "tanh", "KernelRegularizer_4": 7.610078858864631e-05, "ActivityRegularizer_4": 7.260453154063757e-09, "Dropout_4": 2.684125081828228e-06, "Dense_5": 300, "Activation_5": "tanh", "KernelRegularizer_5": 7.924693886522655e-08, "ActivityRegularizer_5": 1.291368726268839e-09, "Dropout_5": 7.001586296943141e-05, "Dense_6": 246, "Activation_6": "relu", "KernelRegularizer_6": 6.592699246705528e-10, "ActivityRegularizer_6": 0.001658225524862451, "Dropout_6": 0.0017288812977684718, "Dense_7": 108, "Activation_7": "tanh", "KernelRegularizer_7": 1.6124604664115463e-05, "ActivityRegularizer_7": 4.1659501272511085e-06, "Dropout_7": 0.0003339266125391638, "Dense_8": 215, "Activation_8": "tanh", "KernelRegularizer_8": 0.022951333082269206, "ActivityRegularizer_8": 0.0012509408125177897, "Dropout_8": 0.0016910903171570707, "Dense_9": 307, "Activation_9": "relu", "KernelRegularizer_9": 0.1246059158392151, "ActivityRegularizer_9": 0.005020124798321124, "Dropout_9": 1.1651321076524025e-05}}, "metrics": {"metrics": {"loss": {"direction": "min", "observations": [{"value": [0.45671966671943665], "step": 12}]}, "accuracy": {"direction": "max", "observations": [{"value": [0.9839572310447693], "step": 12}]}}}, "score": 0.9839572310447693, "best_step": 12, "status": "COMPLETED", "message": null}